namebaseline/__init__.py
namebaseline-0.1.1.dist-info/licenses/LICENSE
namebaseline-0.1.1.dist-info/METADATA
namebaseline-0.1.1.dist-info/WHEEL
namebaseline-0.1.1.dist-info/top_level.txt
namebaseline-0.1.1.dist-info/RECORD
