Metadata-Version: 2.4
Name: namebaseline
Version: 0.1.1
Summary: Python library to analyze names and calculate statistics against a baseline
Author-email: Kris Hardy <kris.hardy@vltbcn.com>
License-Expression: MIT
Keywords: statistics,chi-squared,string-to-float
Classifier: Development Status :: 4 - Beta
Classifier: Intended Audience :: Developers
Classifier: Programming Language :: Python :: 3
Classifier: Topic :: Security
Classifier: Topic :: Software Development :: Libraries :: Python Modules
Requires-Python: >=3.13
License-File: LICENSE
Requires-Dist: pandas
Requires-Dist: numpy
Requires-Dist: scipy
Provides-Extra: dev
Requires-Dist: pytest; extra == "dev"
Requires-Dist: notebook; extra == "dev"
Requires-Dist: matplotlib; extra == "dev"
Requires-Dist: ipympl; extra == "dev"
Requires-Dist: build; extra == "dev"
Requires-Dist: tox; extra == "dev"
Requires-Dist: pandas-stubs; extra == "dev"
Requires-Dist: scipy-stubs; extra == "dev"
Requires-Dist: twine; extra == "dev"
Dynamic: license-file
